{"cameraMode":{"drawMode":0,"name":"Shaded","section":"Shading Mode"},"sceneLighting":true,"audioPlay":false,"sceneViewState":{"showFog":true,"showMaterialUpdate":false,"showSkybox":true,"showFlares":true,"showImageEffects":true,"showParticleSystems":true,"showVisualEffectGraphs":true,"m_FxEnabled":true},"in2DMode":false,"pivot":{"x":-14971.935546875,"y":5074.24560546875,"z":25215.939453125},"rotation":{"x":-0.09224651008844376,"y":0.20579677820205689,"z":0.019488733261823655,"w":0.9740476012229919},"size":18276.02734375,"orthographic":false}